{"name":"Housing","id":"housing;housing","testSteps":[{"number":1,"description":"Given that the user is on the housing page","duration":5146,"startTime":"2023-09-27T14:52:54.493712-05:00[America/Bogota]","screenshots":[{"screenshot":"80a03f9655637b408f7179edcde05673c8ef3405b870d4ea162e18300d790bcf.png","timeStamp":1695844375000},{"screenshot":"52253e0e84dd5b89e0a6407d78f8475ad76e5c8910dce0b79aad1f75e4a10d71.png","timeStamp":1695844379640}],"result":"SUCCESS","precondition":false,"level":0,"children":[{"number":2,"description":"User opens the https://www.booking.com/index.es.html","duration":3565,"startTime":"2023-09-27T14:52:55.454308500-05:00[America/Bogota]","result":"SUCCESS","precondition":false,"level":1}]},{"number":3,"description":"When the user apply the following filters","duration":22599,"startTime":"2023-09-27T14:52:59.642620400-05:00[America/Bogota]","screenshots":[{"screenshot":"b67cb7bf1cdd9ddb2e017005c141de0b029e20d5626fc398a6e4f3c88c830610.png","timeStamp":1695844402242}],"result":"SUCCESS","precondition":false,"level":0,"children":[{"number":4,"description":"User housing","duration":22540,"startTime":"2023-09-27T14:52:59.686480700-05:00[America/Bogota]","screenshots":[{"screenshot":"5d5ba2faddedf22902b943de07e75ec6a2880bc9e282d227f6eeb3df58638758.png","timeStamp":1695844380367},{"screenshot":"b67cb7bf1cdd9ddb2e017005c141de0b029e20d5626fc398a6e4f3c88c830610.png","timeStamp":1695844402226}],"result":"SUCCESS","precondition":false,"level":1,"children":[{"number":5,"description":"User clicks on icons to access a service","duration":4099,"startTime":"2023-09-27T14:53:00.477309200-05:00[America/Bogota]","screenshots":[{"screenshot":"04c40dabaa17f26d59a3562d8b8842256a7b3ef8f216c6038e0509398b3ca634.png","timeStamp":1695844380768},{"screenshot":"1d9ba0db6f594778ce7c30248df8517ac5ce278f62c53f3567656e8d7729107b.png","timeStamp":1695844384577}],"result":"SUCCESS","precondition":false,"level":2},{"number":6,"description":"User clicks on navigation bar to search a housing","duration":681,"startTime":"2023-09-27T14:53:04.581574300-05:00[America/Bogota]","screenshots":[{"screenshot":"1d9ba0db6f594778ce7c30248df8517ac5ce278f62c53f3567656e8d7729107b.png","timeStamp":1695844384607},{"screenshot":"9772d35d2cf40fce1e7e109ce9d7c6dd52cc3b78178abbc0f2cf68290842756f.png","timeStamp":1695844385263}],"result":"SUCCESS","precondition":false,"level":2},{"number":7,"description":"User enters \u0027Colombia\u0027 into navigation bar to search a housing","duration":820,"startTime":"2023-09-27T14:53:05.267310400-05:00[America/Bogota]","screenshots":[{"screenshot":"9772d35d2cf40fce1e7e109ce9d7c6dd52cc3b78178abbc0f2cf68290842756f.png","timeStamp":1695844385291},{"screenshot":"4c23c392c700a54ac131018f3ebb1b66adcd5e9cc75e1b22a5bb1b1d133ee86d.png","timeStamp":1695844386087}],"result":"SUCCESS","precondition":false,"level":2},{"number":8,"description":"User clicks on first result of the city","duration":621,"startTime":"2023-09-27T14:53:06.087841200-05:00[America/Bogota]","screenshots":[{"screenshot":"4c23c392c700a54ac131018f3ebb1b66adcd5e9cc75e1b22a5bb1b1d133ee86d.png","timeStamp":1695844386108},{"screenshot":"77525c416cada9ca1d0ec7acc8a9191309c2c2c6503e25cad99de6691c825138.png","timeStamp":1695844386709}],"result":"SUCCESS","precondition":false,"level":2},{"number":9,"description":"User clicks on select the first date","duration":783,"startTime":"2023-09-27T14:53:06.818137-05:00[America/Bogota]","screenshots":[{"screenshot":"fdbfdcaa9268a3fd6728801f0373d42b871e9399ec38580391f4d7a80bffde89.png","timeStamp":1695844387084},{"screenshot":"2f6db469bff52f4ac73cd860032d52e30e8b0607505cce71acdf4ec22ae25eb5.png","timeStamp":1695844387601}],"result":"SUCCESS","precondition":false,"level":2},{"number":10,"description":"User clicks on select the second date","duration":605,"startTime":"2023-09-27T14:53:07.603332800-05:00[America/Bogota]","screenshots":[{"screenshot":"2f6db469bff52f4ac73cd860032d52e30e8b0607505cce71acdf4ec22ae25eb5.png","timeStamp":1695844387622},{"screenshot":"dc17ad3ded5fb0e9ceb2db69dbdc83dab66fab66edf2796de503880b8b6abc95.png","timeStamp":1695844388209}],"result":"SUCCESS","precondition":false,"level":2},{"number":11,"description":"User clicks on button to open the dropdown","duration":540,"startTime":"2023-09-27T14:53:08.212122400-05:00[America/Bogota]","screenshots":[{"screenshot":"dc17ad3ded5fb0e9ceb2db69dbdc83dab66fab66edf2796de503880b8b6abc95.png","timeStamp":1695844388232},{"screenshot":"1509f7a69912ea853e5cc0794ebcc24d2be793bb301a2e847d8d84e70653a174.png","timeStamp":1695844388752}],"result":"SUCCESS","precondition":false,"level":2},{"number":12,"description":"User clicks on btn to add items to the reservation","duration":533,"startTime":"2023-09-27T14:53:08.754543100-05:00[America/Bogota]","screenshots":[{"screenshot":"1509f7a69912ea853e5cc0794ebcc24d2be793bb301a2e847d8d84e70653a174.png","timeStamp":1695844388772},{"screenshot":"cb383e9562367079118610c2ca5fb8c89483d571200575d225f182a178bb9581.png","timeStamp":1695844389287}],"result":"SUCCESS","precondition":false,"level":2},{"number":13,"description":"User clicks on btn to add items to the reservation","duration":547,"startTime":"2023-09-27T14:53:09.287979100-05:00[America/Bogota]","screenshots":[{"screenshot":"cb383e9562367079118610c2ca5fb8c89483d571200575d225f182a178bb9581.png","timeStamp":1695844389309},{"screenshot":"b04c563a84470f18df40df0fe6c1a3fa3813a3e46dac0b16a8380807a82a7281.png","timeStamp":1695844389834}],"result":"SUCCESS","precondition":false,"level":2},{"number":14,"description":"User clicks on btn to add items to the reservation","duration":482,"startTime":"2023-09-27T14:53:09.837063600-05:00[America/Bogota]","screenshots":[{"screenshot":"b04c563a84470f18df40df0fe6c1a3fa3813a3e46dac0b16a8380807a82a7281.png","timeStamp":1695844389853},{"screenshot":"dd8d7e281423e51217e37f549a7a1deeb0d605b7093cba759e324f13b3659f54.png","timeStamp":1695844390319}],"result":"SUCCESS","precondition":false,"level":2},{"number":15,"description":"User clicks on age of the childs","duration":550,"startTime":"2023-09-27T14:53:10.321401800-05:00[America/Bogota]","screenshots":[{"screenshot":"dd8d7e281423e51217e37f549a7a1deeb0d605b7093cba759e324f13b3659f54.png","timeStamp":1695844390337},{"screenshot":"6272b9eb5084f8b85524d5a5213250be6b3b3d397b258d47881750346ee01e16.png","timeStamp":1695844390872}],"result":"SUCCESS","precondition":false,"level":2},{"number":16,"description":"User selects 6 in age of the childs","duration":621,"startTime":"2023-09-27T14:53:10.876339400-05:00[America/Bogota]","screenshots":[{"screenshot":"6272b9eb5084f8b85524d5a5213250be6b3b3d397b258d47881750346ee01e16.png","timeStamp":1695844390891},{"screenshot":"6272b9eb5084f8b85524d5a5213250be6b3b3d397b258d47881750346ee01e16.png","timeStamp":1695844391497}],"result":"SUCCESS","precondition":false,"level":2},{"number":17,"description":"User clicks on age of the childs","duration":511,"startTime":"2023-09-27T14:53:11.499551200-05:00[America/Bogota]","screenshots":[{"screenshot":"6272b9eb5084f8b85524d5a5213250be6b3b3d397b258d47881750346ee01e16.png","timeStamp":1695844391513},{"screenshot":"163bbc168d9a8d9d562045eec56393ed65edbd5eece814a0d2650967eb341ca9.png","timeStamp":1695844392011}],"result":"SUCCESS","precondition":false,"level":2},{"number":18,"description":"User selects 6 in age of the childs","duration":599,"startTime":"2023-09-27T14:53:12.013406200-05:00[America/Bogota]","screenshots":[{"screenshot":"163bbc168d9a8d9d562045eec56393ed65edbd5eece814a0d2650967eb341ca9.png","timeStamp":1695844392034},{"screenshot":"163bbc168d9a8d9d562045eec56393ed65edbd5eece814a0d2650967eb341ca9.png","timeStamp":1695844392613}],"result":"SUCCESS","precondition":false,"level":2},{"number":19,"description":"User clicks on btn to add items to the reservation","duration":504,"startTime":"2023-09-27T14:53:12.615309100-05:00[America/Bogota]","screenshots":[{"screenshot":"163bbc168d9a8d9d562045eec56393ed65edbd5eece814a0d2650967eb341ca9.png","timeStamp":1695844392629},{"screenshot":"86f52dcd65441792c4b5c556faf00dd83d8d095b344b7964eb9f7eef3bab2200.png","timeStamp":1695844393119}],"result":"SUCCESS","precondition":false,"level":2},{"number":20,"description":"User clicks on btn to search","duration":5584,"startTime":"2023-09-27T14:53:13.121801700-05:00[America/Bogota]","screenshots":[{"screenshot":"86f52dcd65441792c4b5c556faf00dd83d8d095b344b7964eb9f7eef3bab2200.png","timeStamp":1695844393136},{"screenshot":"8075b45995a7db972ad6c908f8dd5df36b39ccb36137fedb3785188ec5dc4140.png","timeStamp":1695844398705}],"result":"SUCCESS","precondition":false,"level":2}]}]},{"number":21,"description":"And the user reserves the number of rooms of the best option","duration":18,"startTime":"2023-09-27T14:53:22.244172600-05:00[America/Bogota]","screenshots":[{"screenshot":"b67cb7bf1cdd9ddb2e017005c141de0b029e20d5626fc398a6e4f3c88c830610.png","timeStamp":1695844402257}],"result":"PENDING","precondition":false,"level":0},{"number":22,"description":"And the user fills the forms to reserve the housing with following data","duration":16,"startTime":"2023-09-27T14:53:22.263379400-05:00[America/Bogota]","result":"IGNORED","precondition":false,"level":0},{"number":23,"description":"And the the user accept terms and clicks on complete the booking","duration":13,"startTime":"2023-09-27T14:53:22.281227600-05:00[America/Bogota]","result":"IGNORED","precondition":false,"level":0},{"number":24,"description":"Then the user should see the booking confirm","duration":10,"startTime":"2023-09-27T14:53:22.295862800-05:00[America/Bogota]","result":"IGNORED","precondition":false,"level":0}],"userStory":{"id":"housing","storyName":"Housing","path":"housing.feature","type":"feature"},"featureTag":{"name":"Housing","type":"feature","displayName":"Housing"},"title":"Housing","description":"","tags":[{"name":"Housing","type":"feature","displayName":"Housing"}],"startTime":"2023-09-27T14:52:50.286375200-05:00[America/Bogota]","duration":32027,"projectKey":"","annotatedResult":"PENDING","sessionId":"3d03533c00a04029511c2db9def7fbcf","driver":"chrome","isManualTestingUpToDate":false,"manual":false,"testSource":"Cucumber","actors":[{"name":"User","can":["browse the web"]}],"result":"PENDING"}