{"name":"Housing","id":"housing;housing","testSteps":[{"number":1,"description":"Given that the user is on the housing page","duration":7696,"startTime":"2023-09-28T09:29:44.511839200-05:00[America/Bogota]","screenshots":[{"screenshot":"80a03f9655637b408f7179edcde05673c8ef3405b870d4ea162e18300d790bcf.png","timeStamp":1695911385006},{"screenshot":"f21cac3e97ddb587885b70a1385e7bdc0594cf0a358925e5c4407a2d9f224715.png","timeStamp":1695911392208}],"result":"SUCCESS","precondition":false,"level":0,"children":[{"number":2,"description":"User opens the https://www.booking.com/index.es.html","duration":6369,"startTime":"2023-09-28T09:29:45.469300500-05:00[America/Bogota]","result":"SUCCESS","precondition":false,"level":1}]},{"number":3,"description":"When the user apply the following filters","duration":21481,"startTime":"2023-09-28T09:29:52.211444500-05:00[America/Bogota]","screenshots":[{"screenshot":"f21cac3e97ddb587885b70a1385e7bdc0594cf0a358925e5c4407a2d9f224715.png","timeStamp":1695911392234}],"exception":{"errorType":"net.thucydides.core.webdriver.exceptions.ElementShouldBePresentException","message":"Expected condition failed: waiting for By.xpath: (//span[@class\u003d\u0027eedba9e88a\u0027])[14] to be present (tried for 20 second(s) with 100 milliseconds interval)\nBuild info: version: \u00273.141.59\u0027, revision: \u0027e82be7d358\u0027, time: \u00272018-11-14T08:17:03\u0027\nSystem info: host: \u0027DESKTOP-QFN6M8D\u0027, ip: \u0027172.18.1.247\u0027, os.name: \u0027Windows 11\u0027, os.arch: \u0027amd64\u0027, os.version: \u002710.0\u0027, java.version: \u002711.0.20.1\u0027\nDriver info: driver.version: unknown","stackTrace":[{"declaringClass":"com.booking.tasks.Housing","methodName":"performAs","fileName":"Housing.java","lineNumber":16},{"declaringClass":"com.booking.stepsdefinitions.HousingStepDefinition","methodName":"theUserApplyTheFollowingFilters","fileName":"HousingStepDefinition.java","lineNumber":24},{"declaringClass":"io.cucumber.java.Invoker","methodName":"doInvoke","fileName":"Invoker.java","lineNumber":66},{"declaringClass":"io.cucumber.java.Invoker","methodName":"invoke","fileName":"Invoker.java","lineNumber":24},{"declaringClass":"io.cucumber.java.AbstractGlueDefinition","methodName":"invokeMethod","fileName":"AbstractGlueDefinition.java","lineNumber":47},{"declaringClass":"io.cucumber.java.JavaStepDefinition","methodName":"execute","fileName":"JavaStepDefinition.java","lineNumber":29},{"declaringClass":"io.cucumber.core.runner.CoreStepDefinition","methodName":"execute","fileName":"CoreStepDefinition.java","lineNumber":66},{"declaringClass":"io.cucumber.core.runner.PickleStepDefinitionMatch","methodName":"runStep","fileName":"PickleStepDefinitionMatch.java","lineNumber":63},{"declaringClass":"io.cucumber.core.runner.TestStep","methodName":"executeStep","fileName":"TestStep.java","lineNumber":92},{"declaringClass":"io.cucumber.core.runner.TestStep","methodName":"run","fileName":"TestStep.java","lineNumber":64},{"declaringClass":"io.cucumber.core.runner.PickleStepTestStep","methodName":"run","fileName":"PickleStepTestStep.java","lineNumber":51},{"declaringClass":"io.cucumber.core.runner.TestCase","methodName":"run","fileName":"TestCase.java","lineNumber":104},{"declaringClass":"io.cucumber.core.runner.Runner","methodName":"runPickle","fileName":"Runner.java","lineNumber":73},{"declaringClass":"io.cucumber.junit.FeatureRunner","methodName":"runChild","fileName":"FeatureRunner.java","lineNumber":135},{"declaringClass":"io.cucumber.junit.FeatureRunner","methodName":"runChild","fileName":"FeatureRunner.java","lineNumber":27},{"declaringClass":"io.cucumber.junit.CucumberSerenityRunner","methodName":"runChild","fileName":"CucumberSerenityRunner.java","lineNumber":258},{"declaringClass":"io.cucumber.junit.CucumberSerenityRunner","methodName":"runChild","fileName":"CucumberSerenityRunner.java","lineNumber":57}],"rootCause":{"errorType":"org.openqa.selenium.TimeoutException","message":"Expected condition failed: waiting for By.xpath: (//span[@class\u003d\u0027eedba9e88a\u0027])[14] to be present (tried for 20 second(s) with 100 milliseconds interval)\nBuild info: version: \u00273.141.59\u0027, revision: \u0027e82be7d358\u0027, time: \u00272018-11-14T08:17:03\u0027\nSystem info: host: \u0027DESKTOP-QFN6M8D\u0027, ip: \u0027172.18.1.247\u0027, os.name: \u0027Windows 11\u0027, os.arch: \u0027amd64\u0027, os.version: \u002710.0\u0027, java.version: \u002711.0.20.1\u0027\nDriver info: driver.version: unknown","stackTrace":[{"declaringClass":"com.booking.tasks.Housing","methodName":"performAs","fileName":"Housing.java","lineNumber":16},{"declaringClass":"com.booking.stepsdefinitions.HousingStepDefinition","methodName":"theUserApplyTheFollowingFilters","fileName":"HousingStepDefinition.java","lineNumber":24},{"declaringClass":"io.cucumber.java.Invoker","methodName":"doInvoke","fileName":"Invoker.java","lineNumber":66},{"declaringClass":"io.cucumber.java.Invoker","methodName":"invoke","fileName":"Invoker.java","lineNumber":24},{"declaringClass":"io.cucumber.java.AbstractGlueDefinition","methodName":"invokeMethod","fileName":"AbstractGlueDefinition.java","lineNumber":47},{"declaringClass":"io.cucumber.java.JavaStepDefinition","methodName":"execute","fileName":"JavaStepDefinition.java","lineNumber":29},{"declaringClass":"io.cucumber.core.runner.CoreStepDefinition","methodName":"execute","fileName":"CoreStepDefinition.java","lineNumber":66},{"declaringClass":"io.cucumber.core.runner.PickleStepDefinitionMatch","methodName":"runStep","fileName":"PickleStepDefinitionMatch.java","lineNumber":63},{"declaringClass":"io.cucumber.core.runner.TestStep","methodName":"executeStep","fileName":"TestStep.java","lineNumber":92},{"declaringClass":"io.cucumber.core.runner.TestStep","methodName":"run","fileName":"TestStep.java","lineNumber":64},{"declaringClass":"io.cucumber.core.runner.PickleStepTestStep","methodName":"run","fileName":"PickleStepTestStep.java","lineNumber":51},{"declaringClass":"io.cucumber.core.runner.TestCase","methodName":"run","fileName":"TestCase.java","lineNumber":104},{"declaringClass":"io.cucumber.core.runner.Runner","methodName":"runPickle","fileName":"Runner.java","lineNumber":73},{"declaringClass":"io.cucumber.junit.FeatureRunner","methodName":"runChild","fileName":"FeatureRunner.java","lineNumber":135},{"declaringClass":"io.cucumber.junit.FeatureRunner","methodName":"runChild","fileName":"FeatureRunner.java","lineNumber":27},{"declaringClass":"io.cucumber.junit.CucumberSerenityRunner","methodName":"runChild","fileName":"CucumberSerenityRunner.java","lineNumber":258},{"declaringClass":"io.cucumber.junit.CucumberSerenityRunner","methodName":"runChild","fileName":"CucumberSerenityRunner.java","lineNumber":57}]}},"result":"FAILURE","precondition":false,"level":0,"children":[{"number":4,"description":"User housing","duration":21416,"startTime":"2023-09-28T09:29:52.251851800-05:00[America/Bogota]","screenshots":[{"screenshot":"f21cac3e97ddb587885b70a1385e7bdc0594cf0a358925e5c4407a2d9f224715.png","timeStamp":1695911392532}],"exception":{"errorType":"net.thucydides.core.webdriver.exceptions.ElementShouldBePresentException","message":"Expected condition failed: waiting for By.xpath: (//span[@class\u003d\u0027eedba9e88a\u0027])[14] to be present (tried for 20 second(s) with 100 milliseconds interval)\nBuild info: version: \u00273.141.59\u0027, revision: \u0027e82be7d358\u0027, time: \u00272018-11-14T08:17:03\u0027\nSystem info: host: \u0027DESKTOP-QFN6M8D\u0027, ip: \u0027172.18.1.247\u0027, os.name: \u0027Windows 11\u0027, os.arch: \u0027amd64\u0027, os.version: \u002710.0\u0027, java.version: \u002711.0.20.1\u0027\nDriver info: driver.version: unknown","stackTrace":[{"declaringClass":"com.booking.tasks.Housing","methodName":"performAs","fileName":"Housing.java","lineNumber":16},{"declaringClass":"com.booking.stepsdefinitions.HousingStepDefinition","methodName":"theUserApplyTheFollowingFilters","fileName":"HousingStepDefinition.java","lineNumber":24},{"declaringClass":"io.cucumber.java.Invoker","methodName":"doInvoke","fileName":"Invoker.java","lineNumber":66},{"declaringClass":"io.cucumber.java.Invoker","methodName":"invoke","fileName":"Invoker.java","lineNumber":24},{"declaringClass":"io.cucumber.java.AbstractGlueDefinition","methodName":"invokeMethod","fileName":"AbstractGlueDefinition.java","lineNumber":47},{"declaringClass":"io.cucumber.java.JavaStepDefinition","methodName":"execute","fileName":"JavaStepDefinition.java","lineNumber":29},{"declaringClass":"io.cucumber.core.runner.CoreStepDefinition","methodName":"execute","fileName":"CoreStepDefinition.java","lineNumber":66},{"declaringClass":"io.cucumber.core.runner.PickleStepDefinitionMatch","methodName":"runStep","fileName":"PickleStepDefinitionMatch.java","lineNumber":63},{"declaringClass":"io.cucumber.core.runner.TestStep","methodName":"executeStep","fileName":"TestStep.java","lineNumber":92},{"declaringClass":"io.cucumber.core.runner.TestStep","methodName":"run","fileName":"TestStep.java","lineNumber":64},{"declaringClass":"io.cucumber.core.runner.PickleStepTestStep","methodName":"run","fileName":"PickleStepTestStep.java","lineNumber":51},{"declaringClass":"io.cucumber.core.runner.TestCase","methodName":"run","fileName":"TestCase.java","lineNumber":104},{"declaringClass":"io.cucumber.core.runner.Runner","methodName":"runPickle","fileName":"Runner.java","lineNumber":73},{"declaringClass":"io.cucumber.junit.FeatureRunner","methodName":"runChild","fileName":"FeatureRunner.java","lineNumber":135},{"declaringClass":"io.cucumber.junit.FeatureRunner","methodName":"runChild","fileName":"FeatureRunner.java","lineNumber":27},{"declaringClass":"io.cucumber.junit.CucumberSerenityRunner","methodName":"runChild","fileName":"CucumberSerenityRunner.java","lineNumber":258},{"declaringClass":"io.cucumber.junit.CucumberSerenityRunner","methodName":"runChild","fileName":"CucumberSerenityRunner.java","lineNumber":57}],"rootCause":{"errorType":"org.openqa.selenium.TimeoutException","message":"Expected condition failed: waiting for By.xpath: (//span[@class\u003d\u0027eedba9e88a\u0027])[14] to be present (tried for 20 second(s) with 100 milliseconds interval)\nBuild info: version: \u00273.141.59\u0027, revision: \u0027e82be7d358\u0027, time: \u00272018-11-14T08:17:03\u0027\nSystem info: host: \u0027DESKTOP-QFN6M8D\u0027, ip: \u0027172.18.1.247\u0027, os.name: \u0027Windows 11\u0027, os.arch: \u0027amd64\u0027, os.version: \u002710.0\u0027, java.version: \u002711.0.20.1\u0027\nDriver info: driver.version: unknown","stackTrace":[{"declaringClass":"com.booking.tasks.Housing","methodName":"performAs","fileName":"Housing.java","lineNumber":16},{"declaringClass":"com.booking.stepsdefinitions.HousingStepDefinition","methodName":"theUserApplyTheFollowingFilters","fileName":"HousingStepDefinition.java","lineNumber":24},{"declaringClass":"io.cucumber.java.Invoker","methodName":"doInvoke","fileName":"Invoker.java","lineNumber":66},{"declaringClass":"io.cucumber.java.Invoker","methodName":"invoke","fileName":"Invoker.java","lineNumber":24},{"declaringClass":"io.cucumber.java.AbstractGlueDefinition","methodName":"invokeMethod","fileName":"AbstractGlueDefinition.java","lineNumber":47},{"declaringClass":"io.cucumber.java.JavaStepDefinition","methodName":"execute","fileName":"JavaStepDefinition.java","lineNumber":29},{"declaringClass":"io.cucumber.core.runner.CoreStepDefinition","methodName":"execute","fileName":"CoreStepDefinition.java","lineNumber":66},{"declaringClass":"io.cucumber.core.runner.PickleStepDefinitionMatch","methodName":"runStep","fileName":"PickleStepDefinitionMatch.java","lineNumber":63},{"declaringClass":"io.cucumber.core.runner.TestStep","methodName":"executeStep","fileName":"TestStep.java","lineNumber":92},{"declaringClass":"io.cucumber.core.runner.TestStep","methodName":"run","fileName":"TestStep.java","lineNumber":64},{"declaringClass":"io.cucumber.core.runner.PickleStepTestStep","methodName":"run","fileName":"PickleStepTestStep.java","lineNumber":51},{"declaringClass":"io.cucumber.core.runner.TestCase","methodName":"run","fileName":"TestCase.java","lineNumber":104},{"declaringClass":"io.cucumber.core.runner.Runner","methodName":"runPickle","fileName":"Runner.java","lineNumber":73},{"declaringClass":"io.cucumber.junit.FeatureRunner","methodName":"runChild","fileName":"FeatureRunner.java","lineNumber":135},{"declaringClass":"io.cucumber.junit.FeatureRunner","methodName":"runChild","fileName":"FeatureRunner.java","lineNumber":27},{"declaringClass":"io.cucumber.junit.CucumberSerenityRunner","methodName":"runChild","fileName":"CucumberSerenityRunner.java","lineNumber":258},{"declaringClass":"io.cucumber.junit.CucumberSerenityRunner","methodName":"runChild","fileName":"CucumberSerenityRunner.java","lineNumber":57}]}},"result":"FAILURE","precondition":false,"level":1,"children":[{"number":5,"description":"User clicks on modal view for registration","duration":21084,"startTime":"2023-09-28T09:29:52.560011100-05:00[America/Bogota]","screenshots":[{"screenshot":"f28a460bae15f5aaf0b0822e474bfa8f0c9ab8ecf12a76f10c4912a5b10d8e29.png","htmlSource":"pagesource325869936341043616.html.txt","timeStamp":1695911413633}],"exception":{"errorType":"net.thucydides.core.webdriver.exceptions.ElementShouldBePresentException","message":"Expected condition failed: waiting for By.xpath: (//span[@class\u003d\u0027eedba9e88a\u0027])[14] to be present (tried for 20 second(s) with 100 milliseconds interval)\nBuild info: version: \u00273.141.59\u0027, revision: \u0027e82be7d358\u0027, time: \u00272018-11-14T08:17:03\u0027\nSystem info: host: \u0027DESKTOP-QFN6M8D\u0027, ip: \u0027172.18.1.247\u0027, os.name: \u0027Windows 11\u0027, os.arch: \u0027amd64\u0027, os.version: \u002710.0\u0027, java.version: \u002711.0.20.1\u0027\nDriver info: driver.version: unknown","stackTrace":[{"declaringClass":"com.booking.tasks.Housing","methodName":"performAs","fileName":"Housing.java","lineNumber":16},{"declaringClass":"com.booking.stepsdefinitions.HousingStepDefinition","methodName":"theUserApplyTheFollowingFilters","fileName":"HousingStepDefinition.java","lineNumber":24},{"declaringClass":"io.cucumber.java.Invoker","methodName":"doInvoke","fileName":"Invoker.java","lineNumber":66},{"declaringClass":"io.cucumber.java.Invoker","methodName":"invoke","fileName":"Invoker.java","lineNumber":24},{"declaringClass":"io.cucumber.java.AbstractGlueDefinition","methodName":"invokeMethod","fileName":"AbstractGlueDefinition.java","lineNumber":47},{"declaringClass":"io.cucumber.java.JavaStepDefinition","methodName":"execute","fileName":"JavaStepDefinition.java","lineNumber":29},{"declaringClass":"io.cucumber.core.runner.CoreStepDefinition","methodName":"execute","fileName":"CoreStepDefinition.java","lineNumber":66},{"declaringClass":"io.cucumber.core.runner.PickleStepDefinitionMatch","methodName":"runStep","fileName":"PickleStepDefinitionMatch.java","lineNumber":63},{"declaringClass":"io.cucumber.core.runner.TestStep","methodName":"executeStep","fileName":"TestStep.java","lineNumber":92},{"declaringClass":"io.cucumber.core.runner.TestStep","methodName":"run","fileName":"TestStep.java","lineNumber":64},{"declaringClass":"io.cucumber.core.runner.PickleStepTestStep","methodName":"run","fileName":"PickleStepTestStep.java","lineNumber":51},{"declaringClass":"io.cucumber.core.runner.TestCase","methodName":"run","fileName":"TestCase.java","lineNumber":104},{"declaringClass":"io.cucumber.core.runner.Runner","methodName":"runPickle","fileName":"Runner.java","lineNumber":73},{"declaringClass":"io.cucumber.junit.FeatureRunner","methodName":"runChild","fileName":"FeatureRunner.java","lineNumber":135},{"declaringClass":"io.cucumber.junit.FeatureRunner","methodName":"runChild","fileName":"FeatureRunner.java","lineNumber":27},{"declaringClass":"io.cucumber.junit.CucumberSerenityRunner","methodName":"runChild","fileName":"CucumberSerenityRunner.java","lineNumber":258},{"declaringClass":"io.cucumber.junit.CucumberSerenityRunner","methodName":"runChild","fileName":"CucumberSerenityRunner.java","lineNumber":57}],"rootCause":{"errorType":"org.openqa.selenium.TimeoutException","message":"Expected condition failed: waiting for By.xpath: (//span[@class\u003d\u0027eedba9e88a\u0027])[14] to be present (tried for 20 second(s) with 100 milliseconds interval)\nBuild info: version: \u00273.141.59\u0027, revision: \u0027e82be7d358\u0027, time: \u00272018-11-14T08:17:03\u0027\nSystem info: host: \u0027DESKTOP-QFN6M8D\u0027, ip: \u0027172.18.1.247\u0027, os.name: \u0027Windows 11\u0027, os.arch: \u0027amd64\u0027, os.version: \u002710.0\u0027, java.version: \u002711.0.20.1\u0027\nDriver info: driver.version: unknown","stackTrace":[{"declaringClass":"com.booking.tasks.Housing","methodName":"performAs","fileName":"Housing.java","lineNumber":16},{"declaringClass":"com.booking.stepsdefinitions.HousingStepDefinition","methodName":"theUserApplyTheFollowingFilters","fileName":"HousingStepDefinition.java","lineNumber":24},{"declaringClass":"io.cucumber.java.Invoker","methodName":"doInvoke","fileName":"Invoker.java","lineNumber":66},{"declaringClass":"io.cucumber.java.Invoker","methodName":"invoke","fileName":"Invoker.java","lineNumber":24},{"declaringClass":"io.cucumber.java.AbstractGlueDefinition","methodName":"invokeMethod","fileName":"AbstractGlueDefinition.java","lineNumber":47},{"declaringClass":"io.cucumber.java.JavaStepDefinition","methodName":"execute","fileName":"JavaStepDefinition.java","lineNumber":29},{"declaringClass":"io.cucumber.core.runner.CoreStepDefinition","methodName":"execute","fileName":"CoreStepDefinition.java","lineNumber":66},{"declaringClass":"io.cucumber.core.runner.PickleStepDefinitionMatch","methodName":"runStep","fileName":"PickleStepDefinitionMatch.java","lineNumber":63},{"declaringClass":"io.cucumber.core.runner.TestStep","methodName":"executeStep","fileName":"TestStep.java","lineNumber":92},{"declaringClass":"io.cucumber.core.runner.TestStep","methodName":"run","fileName":"TestStep.java","lineNumber":64},{"declaringClass":"io.cucumber.core.runner.PickleStepTestStep","methodName":"run","fileName":"PickleStepTestStep.java","lineNumber":51},{"declaringClass":"io.cucumber.core.runner.TestCase","methodName":"run","fileName":"TestCase.java","lineNumber":104},{"declaringClass":"io.cucumber.core.runner.Runner","methodName":"runPickle","fileName":"Runner.java","lineNumber":73},{"declaringClass":"io.cucumber.junit.FeatureRunner","methodName":"runChild","fileName":"FeatureRunner.java","lineNumber":135},{"declaringClass":"io.cucumber.junit.FeatureRunner","methodName":"runChild","fileName":"FeatureRunner.java","lineNumber":27},{"declaringClass":"io.cucumber.junit.CucumberSerenityRunner","methodName":"runChild","fileName":"CucumberSerenityRunner.java","lineNumber":258},{"declaringClass":"io.cucumber.junit.CucumberSerenityRunner","methodName":"runChild","fileName":"CucumberSerenityRunner.java","lineNumber":57}]}},"result":"FAILURE","precondition":false,"level":2}]}]},{"number":6,"description":"And the user reserves the number of rooms of the best option","duration":20,"startTime":"2023-09-28T09:30:13.736855600-05:00[America/Bogota]","result":"SKIPPED","precondition":false,"level":0},{"number":7,"description":"And the user fills the forms to reserve the housing with following data","duration":16,"startTime":"2023-09-28T09:30:13.760933200-05:00[America/Bogota]","result":"SKIPPED","precondition":false,"level":0},{"number":8,"description":"Then the user should see the booking confirm","duration":14,"startTime":"2023-09-28T09:30:13.778505800-05:00[America/Bogota]","result":"SKIPPED","precondition":false,"level":0}],"userStory":{"id":"housing","storyName":"Housing","path":"housing.feature","type":"feature"},"featureTag":{"name":"Housing","type":"feature","displayName":"Housing"},"title":"Housing","description":"","tags":[{"name":"Housing","type":"feature","displayName":"Housing"}],"startTime":"2023-09-28T09:29:40.207128500-05:00[America/Bogota]","duration":33592,"testFailureCause":{"errorType":"net.thucydides.core.webdriver.exceptions.ElementShouldBePresentException","message":"Expected condition failed: waiting for By.xpath: (//span[@class\u003d\u0027eedba9e88a\u0027])[14] to be present (tried for 20 second(s) with 100 milliseconds interval)\nBuild info: version: \u00273.141.59\u0027, revision: \u0027e82be7d358\u0027, time: \u00272018-11-14T08:17:03\u0027\nSystem info: host: \u0027DESKTOP-QFN6M8D\u0027, ip: \u0027172.18.1.247\u0027, os.name: \u0027Windows 11\u0027, os.arch: \u0027amd64\u0027, os.version: \u002710.0\u0027, java.version: \u002711.0.20.1\u0027\nDriver info: driver.version: unknown","stackTrace":[{"declaringClass":"com.booking.tasks.Housing","methodName":"performAs","fileName":"Housing.java","lineNumber":16},{"declaringClass":"com.booking.stepsdefinitions.HousingStepDefinition","methodName":"theUserApplyTheFollowingFilters","fileName":"HousingStepDefinition.java","lineNumber":24},{"declaringClass":"io.cucumber.java.Invoker","methodName":"doInvoke","fileName":"Invoker.java","lineNumber":66},{"declaringClass":"io.cucumber.java.Invoker","methodName":"invoke","fileName":"Invoker.java","lineNumber":24},{"declaringClass":"io.cucumber.java.AbstractGlueDefinition","methodName":"invokeMethod","fileName":"AbstractGlueDefinition.java","lineNumber":47},{"declaringClass":"io.cucumber.java.JavaStepDefinition","methodName":"execute","fileName":"JavaStepDefinition.java","lineNumber":29},{"declaringClass":"io.cucumber.core.runner.CoreStepDefinition","methodName":"execute","fileName":"CoreStepDefinition.java","lineNumber":66},{"declaringClass":"io.cucumber.core.runner.PickleStepDefinitionMatch","methodName":"runStep","fileName":"PickleStepDefinitionMatch.java","lineNumber":63},{"declaringClass":"io.cucumber.core.runner.TestStep","methodName":"executeStep","fileName":"TestStep.java","lineNumber":92},{"declaringClass":"io.cucumber.core.runner.TestStep","methodName":"run","fileName":"TestStep.java","lineNumber":64},{"declaringClass":"io.cucumber.core.runner.PickleStepTestStep","methodName":"run","fileName":"PickleStepTestStep.java","lineNumber":51},{"declaringClass":"io.cucumber.core.runner.TestCase","methodName":"run","fileName":"TestCase.java","lineNumber":104},{"declaringClass":"io.cucumber.core.runner.Runner","methodName":"runPickle","fileName":"Runner.java","lineNumber":73},{"declaringClass":"io.cucumber.junit.FeatureRunner","methodName":"runChild","fileName":"FeatureRunner.java","lineNumber":135},{"declaringClass":"io.cucumber.junit.FeatureRunner","methodName":"runChild","fileName":"FeatureRunner.java","lineNumber":27},{"declaringClass":"io.cucumber.junit.CucumberSerenityRunner","methodName":"runChild","fileName":"CucumberSerenityRunner.java","lineNumber":258},{"declaringClass":"io.cucumber.junit.CucumberSerenityRunner","methodName":"runChild","fileName":"CucumberSerenityRunner.java","lineNumber":57}],"rootCause":{"errorType":"org.openqa.selenium.TimeoutException","message":"Expected condition failed: waiting for By.xpath: (//span[@class\u003d\u0027eedba9e88a\u0027])[14] to be present (tried for 20 second(s) with 100 milliseconds interval)\nBuild info: version: \u00273.141.59\u0027, revision: \u0027e82be7d358\u0027, time: \u00272018-11-14T08:17:03\u0027\nSystem info: host: \u0027DESKTOP-QFN6M8D\u0027, ip: \u0027172.18.1.247\u0027, os.name: \u0027Windows 11\u0027, os.arch: \u0027amd64\u0027, os.version: \u002710.0\u0027, java.version: \u002711.0.20.1\u0027\nDriver info: driver.version: unknown","stackTrace":[{"declaringClass":"com.booking.tasks.Housing","methodName":"performAs","fileName":"Housing.java","lineNumber":16},{"declaringClass":"com.booking.stepsdefinitions.HousingStepDefinition","methodName":"theUserApplyTheFollowingFilters","fileName":"HousingStepDefinition.java","lineNumber":24},{"declaringClass":"io.cucumber.java.Invoker","methodName":"doInvoke","fileName":"Invoker.java","lineNumber":66},{"declaringClass":"io.cucumber.java.Invoker","methodName":"invoke","fileName":"Invoker.java","lineNumber":24},{"declaringClass":"io.cucumber.java.AbstractGlueDefinition","methodName":"invokeMethod","fileName":"AbstractGlueDefinition.java","lineNumber":47},{"declaringClass":"io.cucumber.java.JavaStepDefinition","methodName":"execute","fileName":"JavaStepDefinition.java","lineNumber":29},{"declaringClass":"io.cucumber.core.runner.CoreStepDefinition","methodName":"execute","fileName":"CoreStepDefinition.java","lineNumber":66},{"declaringClass":"io.cucumber.core.runner.PickleStepDefinitionMatch","methodName":"runStep","fileName":"PickleStepDefinitionMatch.java","lineNumber":63},{"declaringClass":"io.cucumber.core.runner.TestStep","methodName":"executeStep","fileName":"TestStep.java","lineNumber":92},{"declaringClass":"io.cucumber.core.runner.TestStep","methodName":"run","fileName":"TestStep.java","lineNumber":64},{"declaringClass":"io.cucumber.core.runner.PickleStepTestStep","methodName":"run","fileName":"PickleStepTestStep.java","lineNumber":51},{"declaringClass":"io.cucumber.core.runner.TestCase","methodName":"run","fileName":"TestCase.java","lineNumber":104},{"declaringClass":"io.cucumber.core.runner.Runner","methodName":"runPickle","fileName":"Runner.java","lineNumber":73},{"declaringClass":"io.cucumber.junit.FeatureRunner","methodName":"runChild","fileName":"FeatureRunner.java","lineNumber":135},{"declaringClass":"io.cucumber.junit.FeatureRunner","methodName":"runChild","fileName":"FeatureRunner.java","lineNumber":27},{"declaringClass":"io.cucumber.junit.CucumberSerenityRunner","methodName":"runChild","fileName":"CucumberSerenityRunner.java","lineNumber":258},{"declaringClass":"io.cucumber.junit.CucumberSerenityRunner","methodName":"runChild","fileName":"CucumberSerenityRunner.java","lineNumber":57}]}},"testFailureClassname":"net.thucydides.core.webdriver.exceptions.ElementShouldBePresentException","testFailureMessage":"Expected condition failed: waiting for By.xpath: (//span[@class\u003d\u0027eedba9e88a\u0027])[14] to be present (tried for 20 second(s) with 100 milliseconds interval)\nBuild info: version: \u00273.141.59\u0027, revision: \u0027e82be7d358\u0027, time: \u00272018-11-14T08:17:03\u0027\nSystem info: host: \u0027DESKTOP-QFN6M8D\u0027, ip: \u0027172.18.1.247\u0027, os.name: \u0027Windows 11\u0027, os.arch: \u0027amd64\u0027, os.version: \u002710.0\u0027, java.version: \u002711.0.20.1\u0027\nDriver info: driver.version: unknown","testFailureSummary":"FAILURE;net.thucydides.core.webdriver.exceptions.ElementShouldBePresentException;Expected condition failed: waiting for By.xpath: (//span[@class\u003d\u0027eedba9e88a\u0027])[14] to be present (tried for 20 second(s) with 100 milliseconds interval)\nBuild info: version: \u00273.141.59\u0027, revision: \u0027e82be7d358\u0027, time: \u00272018-11-14T08:17:03\u0027\nSystem info: host: \u0027DESKTOP-QFN6M8D\u0027, ip: \u0027172.18.1.247\u0027, os.name: \u0027Windows 11\u0027, os.arch: \u0027amd64\u0027, os.version: \u002710.0\u0027, java.version: \u002711.0.20.1\u0027\nDriver info: driver.version: unknown;Housing.java","projectKey":"","annotatedResult":"FAILURE","sessionId":"5d5ed57b13fafd721e9815b4c8d9d2ff","driver":"chrome","isManualTestingUpToDate":false,"manual":false,"testSource":"Cucumber","actors":[{"name":"User","can":["browse the web"]}],"result":"FAILURE"}